jinwu/__init__.py
jinwu/background/__init__.py
jinwu/background/backprior.py
jinwu/cluster/__init__.py
jinwu/cluster/cluster.py
jinwu/core/__init__.py
jinwu/core/datasets.py
jinwu/core/file.py
jinwu/core/fit.py
jinwu/core/gti.py
jinwu/core/heasoft.py
jinwu/core/host.py
jinwu/core/lf.py
jinwu/core/ogip.py
jinwu/core/ops.py
jinwu/core/plot.py
jinwu/core/redshift.py
jinwu/core/time.py
jinwu/core/units.py
jinwu/core/utils.py
jinwu/core/xselect.py
jinwu/data/EP_bkg_Particles_PerCM2_12umCMOS.fits
jinwu/data/EP_bkg_Xray_PerCM2_12umCMOS.fits
jinwu/ep/__init__.py
jinwu/fermi/__init__.py
jinwu/fermi/gbm/GBMObservation.py
jinwu/fermi/gbm/__init__.py
jinwu/ftools/__init__.py
jinwu/ftools/fextract.py
jinwu/ftools/ftgrouppha.py
jinwu/ftools/ftrbnpha.py
jinwu/ftools/ftrbnrmf.py
jinwu/ftools/ftselect.py
jinwu/ftools/grppha.py
jinwu/ftools/region.py
jinwu/ftools/rmf_mapping.py
jinwu/ftools/teldef.py
jinwu/ftools/teldef_helpers.py
jinwu/ftools/xselect_mdb.py
jinwu/lightcurve/__init__.py
jinwu/lightcurve/duration.py
jinwu/lightcurve/lcfake.py
jinwu/lightcurve/trigger.py
jinwu/physics/__init__.py
jinwu/physics/gr.py
jinwu/physics/radiation.py
jinwu/response/__init__.py
jinwu/response/basic.py
jinwu/response/gbm.py
jinwu/spectrum/__init__.py
jinwu/spectrum/specfake.py
jinwu/timing/___init___.py
jinwu-0.0.21.dist-info/licenses/LICENSE
jinwu-0.0.21.dist-info/METADATA
jinwu-0.0.21.dist-info/WHEEL
jinwu-0.0.21.dist-info/top_level.txt
jinwu-0.0.21.dist-info/RECORD
