Metadata-Version: 2.4
Name: jinwu
Version: 0.0.21
Summary: Joint inference and physical modeling toolkit for high-energy transient light-curve and spectral analysis.
Author-email: Xinxiang Sun <sunxx@nao.cas.cn>
License: GPL-3.0-or-later
Project-URL: Homepage, https://github.com/xinxiangsun/jinwu
Project-URL: Repository, https://github.com/xinxiangsun/jinwu
Project-URL: Documentation, https://github.com/xinxiangsun/jinwu/blob/master/README.md
Keywords: astrophysics,transient,lightcurve,spectral,modeling,jinwu
Classifier: License :: OSI Approved :: GNU General Public License v3 or later (GPLv3+)
Classifier: Programming Language :: Python :: 3
Classifier: Programming Language :: Python :: 3 :: Only
Classifier: Programming Language :: Python :: 3.12
Classifier: Intended Audience :: Science/Research
Classifier: Topic :: Scientific/Engineering :: Astronomy
Classifier: Development Status :: 3 - Alpha
Requires-Python: >=3.11
License-File: LICENSE
Requires-Dist: numpy
Requires-Dist: scipy
Requires-Dist: astropy>=7.1.0
Requires-Dist: emcee
Requires-Dist: bxa
Requires-Dist: pymc
Requires-Dist: swiftbat
Requires-Dist: regions
Requires-Dist: ipyaladin
Requires-Dist: requests
Requires-Dist: pillow
Dynamic: license-file
